pdf_craft_sdk/__init__.py
pdf_craft_sdk/batch_types.py
pdf_craft_sdk/client.py
pdf_craft_sdk/enums.py
pdf_craft_sdk/exceptions.py
pdf_craft_sdk/upload_types.py
pdf_craft_sdk-0.4.2.dist-info/METADATA
pdf_craft_sdk-0.4.2.dist-info/WHEEL
pdf_craft_sdk-0.4.2.dist-info/top_level.txt
pdf_craft_sdk-0.4.2.dist-info/RECORD
