Metadata-Version: 2.4
Name: pdf-craft-sdk
Version: 0.4.2
Summary: A Python SDK for PDF Craft API
Home-page: https://github.com/yourusername/pdf-craft-sdk
Author: User
Author-email: user@example.com
Classifier: Programming Language :: Python :: 3
Classifier: License :: OSI Approved :: MIT License
Classifier: Operating System :: OS Independent
Requires-Python: >=3.6
Requires-Dist: requests>=2.25.0
Dynamic: author
Dynamic: author-email
Dynamic: classifier
Dynamic: description
Dynamic: description-content-type
Dynamic: home-page
Dynamic: requires-dist
Dynamic: requires-python
Dynamic: summary
